xbmc.py
xbmcaddon.py
xbmcdrm.py
xbmcgui.py
xbmcplugin.py
xbmcvfs.py
Kodistubs-21.0.0.dist-info/LICENSE.txt
Kodistubs-21.0.0.dist-info/METADATA
Kodistubs-21.0.0.dist-info/WHEEL
Kodistubs-21.0.0.dist-info/top_level.txt
Kodistubs-21.0.0.dist-info/RECORD
