Metadata-Version: 2.1
Name: Kodistubs
Version: 21.0.0
Summary: Stub modules that re-create Kodi Python API
Home-page: https://github.com/romanvm/Kodistubs
Author: Roman Miroshnychenko
Author-email: roman1972@gmail.com
License: GPL-3.0-only
Keywords: kodi documentation inspection
Platform: any
Classifier: Environment :: Plugins
Classifier: License :: OSI Approved :: GNU General Public License v3 (GPLv3)
Classifier: Operating System :: OS Independent
Classifier: Programming Language :: Python :: 3
Classifier: Topic :: Software Development :: Libraries
Classifier: Topic :: Software Development :: Libraries :: Python Modules
Requires-Python: >=3.6
License-File: LICENSE.txt
